CHANGELOG.txt
LICENSE.txt
MANIFEST.in
README.txt
setup.py
CalcBasic.egg-info/PKG-INFO
CalcBasic.egg-info/SOURCES.txt
CalcBasic.egg-info/dependency_links.txt
CalcBasic.egg-info/top_level.txt
abhi/__init__.py
ev/bin/rst2html.py
ev/bin/rst2html4.py
ev/bin/rst2html5.py
ev/bin/rst2latex.py
ev/bin/rst2man.py
ev/bin/rst2odt.py
ev/bin/rst2odt_prepstyles.py
ev/bin/rst2pseudoxml.py
ev/bin/rst2s5.py
ev/bin/rst2xetex.py
ev/bin/rst2xml.py
ev/bin/rstpep2html.py
ev/lib/python3.9/site-packages/six.py
ev/lib/python3.9/site-packages/zipp.py
ev/lib/python3.9/site-packages/Pygments-2.11.2.dist-info/entry_points.txt
ev/lib/python3.9/site-packages/Pygments-2.11.2.dist-info/top_level.txt
ev/lib/python3.9/site-packages/_distutils_hack/__init__.py
ev/lib/python3.9/site-packages/_distutils_hack/override.py
ev/lib/python3.9/site-packages/bleach/__init__.py
ev/lib/python3.9/site-packages/bleach/callbacks.py
ev/lib/python3.9/site-packages/bleach/html5lib_shim.py
ev/lib/python3.9/site-packages/bleach/linkifier.py
ev/lib/python3.9/site-packages/bleach/sanitizer.py
ev/lib/python3.9/site-packages/bleach/utils.py
ev/lib/python3.9/site-packages/bleach-4.1.0.dist-info/top_level.txt
ev/lib/python3.9/site-packages/bleach/_vendor/__init__.py
ev/lib/python3.9/site-packages/bleach/_vendor/parse.py
ev/lib/python3.9/site-packages/bleach/_vendor/vendor.txt
ev/lib/python3.9/site-packages/bleach/_vendor/html5lib/__init__.py
ev/lib/python3.9/site-packages/bleach/_vendor/html5lib/_ihatexml.py
ev/lib/python3.9/site-packages/bleach/_vendor/html5lib/_inputstream.py
ev/lib/python3.9/site-packages/bleach/_vendor/html5lib/_tokenizer.py
ev/lib/python3.9/site-packages/bleach/_vendor/html5lib/_utils.py
ev/lib/python3.9/site-packages/bleach/_vendor/html5lib/constants.py
ev/lib/python3.9/site-packages/bleach/_vendor/html5lib/html5parser.py
ev/lib/python3.9/site-packages/bleach/_vendor/html5lib/serializer.py
ev/lib/python3.9/site-packages/bleach/_vendor/html5lib-1.1.dist-info/top_level.txt
ev/lib/python3.9/site-packages/bleach/_vendor/html5lib/_trie/__init__.py
ev/lib/python3.9/site-packages/bleach/_vendor/html5lib/_trie/_base.py
ev/lib/python3.9/site-packages/bleach/_vendor/html5lib/_trie/py.py
ev/lib/python3.9/site-packages/bleach/_vendor/html5lib/filters/__init__.py
ev/lib/python3.9/site-packages/bleach/_vendor/html5lib/filters/alphabeticalattributes.py
ev/lib/python3.9/site-packages/bleach/_vendor/html5lib/filters/base.py
ev/lib/python3.9/site-packages/certifi-2021.10.8.dist-info/top_level.txt
ev/lib/python3.9/site-packages/charset_normalizer-2.0.12.dist-info/entry_points.txt
ev/lib/python3.9/site-packages/charset_normalizer-2.0.12.dist-info/top_level.txt
ev/lib/python3.9/site-packages/commonmark-0.9.1.dist-info/entry_points.txt
ev/lib/python3.9/site-packages/commonmark-0.9.1.dist-info/top_level.txt
ev/lib/python3.9/site-packages/docutils-0.18.1.dist-info/COPYING.txt
ev/lib/python3.9/site-packages/docutils-0.18.1.dist-info/top_level.txt
ev/lib/python3.9/site-packages/idna-3.3.dist-info/top_level.txt
ev/lib/python3.9/site-packages/importlib_metadata-4.11.3.dist-info/top_level.txt
ev/lib/python3.9/site-packages/keyring-23.5.0.dist-info/entry_points.txt
ev/lib/python3.9/site-packages/keyring-23.5.0.dist-info/top_level.txt
ev/lib/python3.9/site-packages/packaging-21.3.dist-info/top_level.txt
ev/lib/python3.9/site-packages/pip-21.2.4.dist-info/LICENSE.txt
ev/lib/python3.9/site-packages/pip-21.2.4.dist-info/entry_points.txt
ev/lib/python3.9/site-packages/pip-21.2.4.dist-info/top_level.txt
ev/lib/python3.9/site-packages/pkginfo-1.8.2.dist-info/LICENSE.txt
ev/lib/python3.9/site-packages/pkginfo-1.8.2.dist-info/entry_points.txt
ev/lib/python3.9/site-packages/pkginfo-1.8.2.dist-info/top_level.txt
ev/lib/python3.9/site-packages/pyparsing-3.0.7.dist-info/top_level.txt
ev/lib/python3.9/site-packages/readme_renderer-34.0.dist-info/entry_points.txt
ev/lib/python3.9/site-packages/readme_renderer-34.0.dist-info/top_level.txt
ev/lib/python3.9/site-packages/requests-2.27.1.dist-info/top_level.txt
ev/lib/python3.9/site-packages/requests_toolbelt-0.9.1.dist-info/top_level.txt
ev/lib/python3.9/site-packages/rfc3986-2.0.0.dist-info/top_level.txt
ev/lib/python3.9/site-packages/setuptools-58.1.0.dist-info/entry_points.txt
ev/lib/python3.9/site-packages/setuptools-58.1.0.dist-info/top_level.txt
ev/lib/python3.9/site-packages/six-1.16.0.dist-info/top_level.txt
ev/lib/python3.9/site-packages/twine-4.0.0.dist-info/entry_points.txt
ev/lib/python3.9/site-packages/twine-4.0.0.dist-info/top_level.txt
ev/lib/python3.9/site-packages/urllib3-1.26.9.dist-info/LICENSE.txt
ev/lib/python3.9/site-packages/urllib3-1.26.9.dist-info/top_level.txt
ev/lib/python3.9/site-packages/webencodings-0.5.1.dist-info/top_level.txt
ev/lib/python3.9/site-packages/zipp-3.8.0.dist-info/top_level.txt